heep/__init__.py
heep-1.0.2.dist-info/LICENSE
heep-1.0.2.dist-info/METADATA
heep-1.0.2.dist-info/WHEEL
heep-1.0.2.dist-info/top_level.txt
heep-1.0.2.dist-info/RECORD
