Metadata-Version: 2.1
Name: heep
Version: 1.0.2
Summary: Sophisticate Heap
Home-page: https://pypi.org/project/heep/
Author: khiat Mohammed Abderrezzak
Author-email: khiat.dev@gmail.com
License: MIT
Keywords: heap
Classifier: Programming Language :: Python :: 3
Classifier: Operating System :: OS Independent
Classifier: License :: OSI Approved :: MIT License
Requires-Python: >=3.6
License-File: LICENSE
Requires-Dist: tabulate (>=0.9.0)
